{
  "date": "2026-07-06",
  "market_summary": "隔夜美股因独立日休市，但纳指期货大涨1.39%，标普期货涨0.5%，外围情绪偏暖。然而，A股宽基指数已全部触发卖出信号，市场整体处于调整周期。主线报告明确电子/半导体进入P3退潮期，资金大幅净流出244亿。在此背景下，今日战法模式判定为【防守反击，独立景气方向择优低吸】，总仓位严格限制在30%以下，保留至少35%现金。重点聚焦与科技退潮低相关的创新药、能源设备及业绩爆发的独立景气方向。",
  "bad_news_table": [
    {
      "source": "主线报告确认退潮",
      "content": "电子/半导体净流出244亿居首，PCB方向与主线背离",
      "exclude": "A股PCB/半导体：深南电路、景旺电子、东山精密等"
    },
    {
      "source": "个股重大风险事件",
      "content": "恒立液压董事长被立案留置；东山精密控制权拟变更；航天环宇7月6日起股东减持1%",
      "exclude": "恒立液压、东山精密、航天环宇"
    }
  ],
  "catalyst_list": [
    {
      "title": "1. 创新药出海与估值修复",
      "content": "科技股分化及加息预期降低利于创新药，泽璟制药ZG006与艾伯维出海授权是国内Biotech标志性交易，DLL3靶点认知存在巨大预期差。ADC药物全球领先，国内政策与商保支持有望打造百亿大单品，板块迎来高景气与估值底部修复双击。"
    },
    {
      "title": "2. AI算力基建外溢与北美缺电",
      "content": "北美数据中心电价飙升6倍，美国最大电网启动二级紧急警报。杰瑞股份凭借北美燃气轮机发电机组订单（累计超9亿美元），成为算力基建电力配套的核心受益标的，AI算力→电力配套的逻辑尚未被市场充分认知，且消息面干净。"
    },
    {
      "title": "3. 光通信量价齐升与中报大爆发",
      "content": "永鼎股份Q2单季业绩大爆发，光通信板块贡献绝大部分增量。AI算力需求带动光纤量价齐升，高附加值的800G/1.6T光模块及自研光芯片占比提升，在手订单充沛（超40亿），业绩拐点确立，光通信景气度从光模块往光纤光缆传导。"
    }
  ],
  "top_three_stocks": [
    {
      "rank": 1,
      "code": "688266",
      "name": "泽璟制药",
      "logic": "唯一同时满足“未列入异动公告+Q1业绩爆发+K线三连阳+机构深度控盘”的标的。ZG006与艾伯维重磅出海授权是国内Biotech标志性交易，DLL3靶点认知存在巨大预期差，短期与中期确定性均较强。今日龙虎榜无符合市值的机构候选，资金证据偏弱，但该股机构底仓深厚，逻辑独立于科技退潮。",
      "score": 92,
      "price_condition": "竞价开盘幅度在-2%至3%之间，量比>1.5，分时承接有力则介入；若低开则等翻红且站稳分时均线后右侧低吸；若高开超5%追高风险大，放弃追高。",
      "k_features": "K线呈三连阳，量价温和，均线多头排列，底部筹码锁定良好，阳多阴少。",
      "market_cap": "约 180 亿",
      "pct_change_5d": "+15%"
    },
    {
      "rank": 2,
      "code": "002353",
      "name": "杰瑞股份",
      "logic": "北美数据中心燃气轮机订单超9亿美元，AI算力→电力配套的逻辑未被市场充分认知。未列入异动公告，消息面干净，属于低位启动的独立方向，有望承接从科技板块撤离的再配置资金。",
      "score": 88,
      "price_condition": "竞价平开至小幅高开（0%至2%），量比>1.2，回踩5日均线不破可低吸；若大幅高开超4%则等待回踩分时均线确认支撑。",
      "k_features": "底部温和放量企稳，K线在21日均线附近获得支撑，筹码逐步集中。",
      "market_cap": "约 250 亿",
      "pct_change_5d": "+8%"
    },
    {
      "rank": 3,
      "code": "600105",
      "name": "永鼎股份",
      "logic": "中报预告Q2单季大爆发，净利润预增57%-120%，环比大幅跳升。光通信板块量价齐升贡献绝大部分增量，800G/1.6T高附加值产品占比提升。虽然科技板块整体退潮，但该股业绩超预期且处于低位，具备独立博弈价值。",
      "score": 85,
      "price_condition": "竞价低开或平开（-2%至1%），量比>2.0，分时放量上攻可跟随；若高开超3%追高风险大，需等回踩分时均线不破再介入。",
      "k_features": "长期底部震荡，近期放量突破短期均线，筹码开始密集，阳线多于阴线。",
      "market_cap": "约 90 亿",
      "pct_change_5d": "+5%"
    }
  ],
  "excluded_stocks": [
    {
      "name": "东山精密",
      "reason": "7月6日公告控制权拟变更属重大不确定性，且PCB方向正处P3退潮期，坚决回避。"
    },
    {
      "name": "航天环宇",
      "reason": "7月6日起股东减持1%窗口开启，坚决回避。"
    },
    {
      "name": "恒立液压",
      "reason": "董事长被立案留置属重大风险事件，需高度警惕，直接排除。"
    },
    {
      "name": "深南电路",
      "reason": "PCB方向与主线完全背离，处于退潮期，坚决回避。"
    }
  ],
  "watch_list": [
    {
      "name": "江波龙 (301308)",
      "direction": "存储涨价",
      "logic": "上半年净利润预增超622倍，存储产业链景气度持续扩散，Q2环比大增。",
      "trigger": "若科技板块企稳，存储方向有望率先反弹，观察后续量能配合。"
    },
    {
      "name": "拓荆科技 (688072)",
      "direction": "先进封装",
      "logic": "韬定律V2明确混合键合落地，国内唯一能量产W2W混合键合设备，长期弹性最大。",
      "trigger": "等待半导体设备板块整体企稳信号，观察主力资金回流情况。"
    }
  ],
  "operation_summary": "1. 总仓位严格控制在30%以下，保留35%以上现金应对板块轮动风险。2. 方向第一，优先配置与AI硬件杀跌低相关的独立方向（创新药、能源设备）。3. 今日龙虎榜无符合市值的机构候选，资金证据偏弱，操作上以低吸为主，切忌追高。4. 坚决回避PCB退潮方向及有重大风险事件的个股，不盲目抄底半导体。",
  "full_markdown_report": "# 湖滨四季·今日选股结果（2026年7月6日）\n> **报告日期**：2026-07-06（周一）  \n> **战法模式**：防守反击，独立景气方向择优低吸  \n> **总仓位建议**：30%以下，保留35%以上现金  \n\n---\n\n## 一、市场环境与模式判定\n隔夜美股因独立日休市，但纳指期货大涨1.39%，标普期货涨0.5%，外围情绪偏暖。然而，A股宽基指数已全部触发卖出信号，市场整体处于调整周期。主线报告明确电子/半导体进入P3退潮期，资金大幅净流出244亿。在此背景下，今日战法模式判定为【防守反击，独立景气方向择优低吸】，总仓位严格限制在30%以下，保留至少35%现金。重点聚焦与科技退潮低相关的创新药、能源设备及业绩爆发的独立景气方向。\n\n## 二、盘前利空与硬排除清单\n| 利空来源 | 具体表现 | 排除板块/个股 |\n| :--- | :--- | :--- |\n| 主线报告确认退潮 | 电子/半导体净流出244亿居首，PCB方向与主线背离 | A股PCB/半导体：深南电路、景旺电子、东山精密等 |\n| 个股重大风险事件 | 恒立液压董事长被立案留置；东山精密控制权拟变更；航天环宇7月6日起股东减持1% | 恒立液压、东山精密、航天环宇 |\n\n---\n\n## 三、核心催化逻辑梳理\n### 1. 创新药出海与估值修复\n科技股分化及加息预期降低利于创新药，泽璟制药ZG006与艾伯维出海授权是国内Biotech标志性交易，DLL3靶点认知存在巨大预期差。ADC药物全球领先，国内政策与商保支持有望打造百亿大单品，板块迎来高景气与估值底部修复双击。\n\n### 2. AI算力基建外溢与北美缺电\n北美数据中心电价飙升6倍，美国最大电网启动二级紧急警报。杰瑞股份凭借北美燃气轮机发电机组订单（累计超9亿美元），成为算力基建电力配套的核心受益标的，AI算力→电力配套的逻辑尚未被市场充分认知。\n\n### 3. 光通信量价齐升与中报大爆发\n永鼎股份Q2单季业绩大爆发，光通信板块贡献绝大部分增量。AI算力需求带动光纤量价齐升，高附加值的800G/1.6T光模块及自研光芯片占比提升，在手订单充沛（超40亿），业绩拐点确立。\n\n---\n\n## 四、今日首选三标（按评分排序）\n| 排名 | 代码 | 名称 | 核心逻辑 | 综合评分 | 流通市值 | 近5日涨幅 |\n| :---: | :---: | :---: | :--- | :---: | :---: | :---: |\n| 1 | 688266 | 泽璟制药 | 创新药出海标杆，未列入异动公告，业绩爆发+机构控盘 | 92 | 180亿 | +15% |\n| 2 | 002353 | 杰瑞股份 | 北美数据中心燃气轮机大单，AI算力电力配套逻辑 | 88 | 250亿 | +8% |\n| 3 | 600105 | 永鼎股份 | Q2单季大爆发，光通信量价齐升，业绩拐点确立 | 85 | 90亿 | +5% |\n\n### 详细介入条件与筹码特征\n**Top 1: 泽璟制药 (688266)**\n- **介入条件**：竞价开盘幅度在-2%至3%之间，量比>1.5，分时承接有力则介入；若低开则等翻红且站稳分时均线后右侧低吸；若高开超5%追高风险大，放弃追高。\n- **K线及筹码特征**：K线呈三连阳，量价温和，均线多头排列，底部筹码锁定良好，阳多阴少。\n\n**Top 2: 杰瑞股份 (002353)**\n- **介入条件**：竞价平开至小幅高开（0%至2%），量比>1.2，回踩5日均线不破可低吸；若大幅高开超4%则等待回踩分时均线确认支撑。\n- **K线及筹码特征**：底部温和放量企稳，K线在21日均线附近获得支撑，筹码逐步集中。\n\n**Top 3: 永鼎股份 (600105)**\n- **介入条件**：竞价低开或平开（-2%至1%），量比>2.0，分时放量上攻可跟随；若高开超3%追高风险大，需等回踩分时均线不破再介入。\n- **K线及筹码特征**：长期底部震荡，近期放量突破短期均线，筹码开始密集，阳线多于阴线。\n\n---\n\n## 五、重点放弃/排除标的\n| 个股名称 | 排除原因 |\n|---|---|\n| 东山精密 | 7月6日公告控制权拟变更属重大不确定性，且PCB方向正处P3退潮期，坚决回避。 |\n| 航天环宇 | 7月6日起股东减持1%窗口开启，坚决回避。 |\n| 恒立液压 | 董事长被立案留置属重大风险事件，需高度警惕，直接排除。 |\n| 深南电路 | PCB方向与主线完全背离，处于退潮期，坚决回避。 |\n\n---\n\n## 六、后续观察池\n| 个股名称 (代码) | 所处方向 | 核心逻辑 | 后续观察点 |\n|---|---|---|---|\n| 江波龙 (301308) | 存储涨价 | 上半年净利润预增超622倍，存储产业链景气度持续扩散，Q2环比大增。 | 若科技板块企稳，存储方向有望率先反弹，观察后续量能配合。 |\n| 拓荆科技 (688072) | 先进封装 | 韬定律V2明确混合键合落地，国内唯一能量产W2W混合键合设备，长期弹性最大。 | 等待半导体设备板块整体企稳信号，观察主力资金回流情况。 |\n\n---\n\n## 七、今日操作核心总结\n1. 总仓位严格控制在30%以下，保留35%以上现金应对板块轮动风险。\n2. 方向第一，优先配置与AI硬件杀跌低相关的独立方向（创新药、能源设备）。\n3. 今日龙虎榜无符合市值的机构候选，资金证据偏弱，操作上以低吸为主，切忌追高。\n4. 坚决回避PCB退潮方向及有重大风险事件的个股，不盲目抄底半导体。"
}